{
  "renames": {
    "/bangs/1.png": "/bangs/bangs_01.png",
    "/bangs/10.png": "/bangs/bangs_10.png",
    "/bangs/11.png": "/bangs/bangs_11.png",
    "/bangs/12.png": "/bangs/bangs_12.png",
    "/bangs/13.png": "/bangs/bangs_13.png",
    "/bangs/2.png": "/bangs/bangs_02.png",
    "/bangs/3.png": "/bangs/bangs_03.png",
    "/bangs/4.png": "/bangs/bangs_04.png",
    "/bangs/5.png": "/bangs/bangs_05.png",
    "/bangs/6.png": "/bangs/bangs_06.png",
    "/bangs/7.png": "/bangs/bangs_07.png",
    "/bangs/8.png": "/bangs/bangs_08.png",
    "/bangs/9.png": "/bangs/bangs_09.png",
    "/bangs/COLOR/1.png": "/bangs/COLOR/bangs_01.png",
    "/bangs/COLOR/10.png": "/bangs/COLOR/bangs_10.png",
    "/bangs/COLOR/10b.png": "/bangs/COLOR/bangs_10b.png",
    "/bangs/COLOR/10c.png": "/bangs/COLOR/bangs_10c.png",
    "/bangs/COLOR/10d.png": "/bangs/COLOR/bangs_10d.png",
    "/bangs/COLOR/10e.png": "/bangs/COLOR/bangs_10e.png",
    "/bangs/COLOR/10f.png": "/bangs/COLOR/bangs_10f.png",
    "/bangs/COLOR/10g.png": "/bangs/COLOR/bangs_10g.png",
    "/bangs/COLOR/10h.png": "/bangs/COLOR/bangs_10h.png",
    "/bangs/COLOR/11.png": "/bangs/COLOR/bangs_11.png",
    "/bangs/COLOR/11b.png": "/bangs/COLOR/bangs_11b.png",
    "/bangs/COLOR/11c.png": "/bangs/COLOR/bangs_11c.png",
    "/bangs/COLOR/11d.png": "/bangs/COLOR/bangs_11d.png",
    "/bangs/COLOR/11e.png": "/bangs/COLOR/bangs_11e.png",
    "/bangs/COLOR/11f.png": "/bangs/COLOR/bangs_11f.png",
    "/bangs/COLOR/11g.png": "/bangs/COLOR/bangs_11g.png",
    "/bangs/COLOR/11h.png": "/bangs/COLOR/bangs_11h.png",
    "/bangs/COLOR/12.png": "/bangs/COLOR/bangs_12.png",
    "/bangs/COLOR/12b.png": "/bangs/COLOR/bangs_12b.png",
    "/bangs/COLOR/12c.png": "/bangs/COLOR/bangs_12c.png",
    "/bangs/COLOR/12d.png": "/bangs/COLOR/bangs_12d.png",
    "/bangs/COLOR/12e.png": "/bangs/COLOR/bangs_12e.png",
    "/bangs/COLOR/12f.png": "/bangs/COLOR/bangs_12f.png",
    "/bangs/COLOR/12g.png": "/bangs/COLOR/bangs_12g.png",
    "/bangs/COLOR/12h.png": "/bangs/COLOR/bangs_12h.png",
    "/bangs/COLOR/13.png": "/bangs/COLOR/bangs_13.png",
    "/bangs/COLOR/13b.png": "/bangs/COLOR/bangs_13b.png",
    "/bangs/COLOR/13c.png": "/bangs/COLOR/bangs_13c.png",
    "/bangs/COLOR/13d.png": "/bangs/COLOR/bangs_13d.png",
    "/bangs/COLOR/13e.png": "/bangs/COLOR/bangs_13e.png",
    "/bangs/COLOR/13f.png": "/bangs/COLOR/bangs_13f.png",
    "/bangs/COLOR/13g.png": "/bangs/COLOR/bangs_13g.png",
    "/bangs/COLOR/13h.png": "/bangs/COLOR/bangs_13h.png",
    "/bangs/COLOR/1b.png": "/bangs/COLOR/bangs_01b.png",
    "/bangs/COLOR/1c.png": "/bangs/COLOR/bangs_01c.png",
    "/bangs/COLOR/1d.png": "/bangs/COLOR/bangs_01d.png",
    "/bangs/COLOR/1e.png": "/bangs/COLOR/bangs_01e.png",
    "/bangs/COLOR/1f.png": "/bangs/COLOR/bangs_01f.png",
    "/bangs/COLOR/1g.png": "/bangs/COLOR/bangs_01g.png",
    "/bangs/COLOR/1h.png": "/bangs/COLOR/bangs_01h.png",
    "/bangs/COLOR/2.png": "/bangs/COLOR/bangs_02.png",
    "/bangs/COLOR/2b.png": "/bangs/COLOR/bangs_02b.png",
    "/bangs/COLOR/2c.png": "/bangs/COLOR/bangs_02c.png",
    "/bangs/COLOR/2d.png": "/bangs/COLOR/bangs_02d.png",
    "/bangs/COLOR/2e.png": "/bangs/COLOR/bangs_02e.png",
    "/bangs/COLOR/2f.png": "/bangs/COLOR/bangs_02f.png",
    "/bangs/COLOR/2g.png": "/bangs/COLOR/bangs_02g.png",
    "/bangs/COLOR/2h.png": "/bangs/COLOR/bangs_02h.png",
    "/bangs/COLOR/3.png": "/bangs/COLOR/bangs_03.png",
    "/bangs/COLOR/3b.png": "/bangs/COLOR/bangs_03b.png",
    "/bangs/COLOR/3c.png": "/bangs/COLOR/bangs_03c.png",
    "/bangs/COLOR/3d.png": "/bangs/COLOR/bangs_03d.png",
    "/bangs/COLOR/3e.png": "/bangs/COLOR/bangs_03e.png",
    "/bangs/COLOR/3f.png": "/bangs/COLOR/bangs_03f.png",
    "/bangs/COLOR/3g.png": "/bangs/COLOR/bangs_03g.png",
    "/bangs/COLOR/3h.png": "/bangs/COLOR/bangs_03h.png",
    "/bangs/COLOR/4.png": "/bangs/COLOR/bangs_04.png",
    "/bangs/COLOR/4b.png": "/bangs/COLOR/bangs_04b.png",
    "/bangs/COLOR/4c.png": "/bangs/COLOR/bangs_04c.png",
    "/bangs/COLOR/4d.png": "/bangs/COLOR/bangs_04d.png",
    "/bangs/COLOR/4e.png": "/bangs/COLOR/bangs_04e.png",
    "/bangs/COLOR/4f.png": "/bangs/COLOR/bangs_04f.png",
    "/bangs/COLOR/4g.png": "/bangs/COLOR/bangs_04g.png",
    "/bangs/COLOR/4h.png": "/bangs/COLOR/bangs_04h.png",
    "/bangs/COLOR/5.png": "/bangs/COLOR/bangs_05.png",
    "/bangs/COLOR/5b.png": "/bangs/COLOR/bangs_05b.png",
    "/bangs/COLOR/5c.png": "/bangs/COLOR/bangs_05c.png",
    "/bangs/COLOR/5d.png": "/bangs/COLOR/bangs_05d.png",
    "/bangs/COLOR/5e.png": "/bangs/COLOR/bangs_05e.png",
    "/bangs/COLOR/5f.png": "/bangs/COLOR/bangs_05f.png",
    "/bangs/COLOR/5g.png": "/bangs/COLOR/bangs_05g.png",
    "/bangs/COLOR/5h.png": "/bangs/COLOR/bangs_05h.png",
    "/bangs/COLOR/6.png": "/bangs/COLOR/bangs_06.png",
    "/bangs/COLOR/6b.png": "/bangs/COLOR/bangs_06b.png",
    "/bangs/COLOR/6c.png": "/bangs/COLOR/bangs_06c.png",
    "/bangs/COLOR/6d.png": "/bangs/COLOR/bangs_06d.png",
    "/bangs/COLOR/6e.png": "/bangs/COLOR/bangs_06e.png",
    "/bangs/COLOR/6f.png": "/bangs/COLOR/bangs_06f.png",
    "/bangs/COLOR/6g.png": "/bangs/COLOR/bangs_06g.png",
    "/bangs/COLOR/6h.png": "/bangs/COLOR/bangs_06h.png",
    "/bangs/COLOR/7.png": "/bangs/COLOR/bangs_07.png",
    "/bangs/COLOR/7b.png": "/bangs/COLOR/bangs_07b.png",
    "/bangs/COLOR/7c.png": "/bangs/COLOR/bangs_07c.png",
    "/bangs/COLOR/7d.png": "/bangs/COLOR/bangs_07d.png",
    "/bangs/COLOR/7e.png": "/bangs/COLOR/bangs_07e.png",
    "/bangs/COLOR/7f.png": "/bangs/COLOR/bangs_07f.png",
    "/bangs/COLOR/7g.png": "/bangs/COLOR/bangs_07g.png",
    "/bangs/COLOR/7h.png": "/bangs/COLOR/bangs_07h.png",
    "/bangs/COLOR/8.png": "/bangs/COLOR/bangs_08.png",
    "/bangs/COLOR/8b.png": "/bangs/COLOR/bangs_08b.png",
    "/bangs/COLOR/8c.png": "/bangs/COLOR/bangs_08c.png",
    "/bangs/COLOR/8d.png": "/bangs/COLOR/bangs_08d.png",
    "/bangs/COLOR/8e.png": "/bangs/COLOR/bangs_08e.png",
    "/bangs/COLOR/8f.png": "/bangs/COLOR/bangs_08f.png",
    "/bangs/COLOR/8g.png": "/bangs/COLOR/bangs_08g.png",
    "/bangs/COLOR/8h.png": "/bangs/COLOR/bangs_08h.png",
    "/bangs/COLOR/9.png": "/bangs/COLOR/bangs_09.png",
    "/bangs/COLOR/9b.png": "/bangs/COLOR/bangs_09b.png",
    "/bangs/COLOR/9c.png": "/bangs/COLOR/bangs_09c.png",
    "/bangs/COLOR/9d.png": "/bangs/COLOR/bangs_09d.png",
    "/bangs/COLOR/9e.png": "/bangs/COLOR/bangs_09e.png",
    "/bangs/COLOR/9f.png": "/bangs/COLOR/bangs_09f.png",
    "/bangs/COLOR/9g.png": "/bangs/COLOR/bangs_09g.png",
    "/bangs/COLOR/9h.png": "/bangs/COLOR/bangs_09h.png",
    "/BEARD/1.png": "/BEARD/beard_01.png",
    "/BEARD/2.png": "/BEARD/beard_02.png",
    "/BEARD/3.png": "/BEARD/beard_03.png",
    "/BEARD/4.png": "/BEARD/beard_04.png",
    "/BEARD/5.png": "/BEARD/beard_05.png",
    "/body/1.png": "/body/body_01.png",
    "/body/10.png": "/body/body_10.png",
    "/body/11.png": "/body/body_11.png",
    "/body/12.png": "/body/body_12.png",
    "/body/13.png": "/body/body_13.png",
    "/body/14.png": "/body/body_14.png",
    "/body/15.png": "/body/body_15.png",
    "/body/16.png": "/body/body_16.png",
    "/body/17.png": "/body/body_17.png",
    "/body/18.png": "/body/body_18.png",
    "/body/19.png": "/body/body_19.png",
    "/body/2.png": "/body/body_02.png",
    "/body/20.png": "/body/body_20.png",
    "/body/21.png": "/body/body_21.png",
    "/body/22.png": "/body/body_22.png",
    "/body/23.png": "/body/body_23.png",
    "/body/24.png": "/body/body_24.png",
    "/body/25.png": "/body/body_25.png",
    "/body/26.png": "/body/body_26.png",
    "/body/27.png": "/body/body_27.png",
    "/body/28.png": "/body/body_28.png",
    "/body/29.png": "/body/body_29.png",
    "/body/3.png": "/body/body_03.png",
    "/body/4.png": "/body/body_04.png",
    "/body/5.png": "/body/body_05.png",
    "/body/6.png": "/body/body_06.png",
    "/body/7.png": "/body/body_07.png",
    "/body/8.png": "/body/body_08.png",
    "/body/9.png": "/body/body_09.png",
    "/body/arm_left.png": "/body/body_arm_left.png",
    "/body/arm_right.png": "/body/body_arm_right.png",
    "/body/belly.png": "/body/body_belly.png",
    "/body/boobs.png": "/body/body_boobs.png",
    "/body/chest.png": "/body/body_chest.png",
    "/body/feet_left.png": "/body/body_feet_left.png",
    "/body/feet_right.png": "/body/body_feet_right.png",
    "/body/full.png": "/body/body_full.png",
    "/body/hand_left.png": "/body/body_hand_left.png",
    "/body/hand_right.png": "/body/body_hand_right.png",
    "/body/head.png": "/body/body_head.png",
    "/body/leg_left.png": "/body/body_leg_left.png",
    "/body/leg_right.png": "/body/body_leg_right.png",
    "/body/muscles.png": "/body/body_muscles.png",
    "/body/neck.png": "/body/body_neck.png",
    "/body/pecs.png": "/body/body_pecs.png",
    "/body/thight_left.png": "/body/body_thight_left.png",
    "/body/thight_right.png": "/body/body_thight_right.png",
    "/bottom/1.png": "/bottom/bottom_01.png",
    "/bottom/2.png": "/bottom/bottom_02.png",
    "/bottom/3.png": "/bottom/bottom_03.png",
    "/bottom/4.png": "/bottom/bottom_04.png",
    "/bottom/5.png": "/bottom/bottom_05.png",
    "/bottom/6.png": "/bottom/bottom_06.png",
    "/bottom/7.png": "/bottom/bottom_07.png",
    "/bottom/8.png": "/bottom/bottom_08.png",
    "/bottom/color/1.png": "/bottom/color/bottom_01.png",
    "/bottom/color/2.png": "/bottom/color/bottom_02.png",
    "/bottom/color/3.png": "/bottom/color/bottom_03.png",
    "/bottom/color/4.png": "/bottom/color/bottom_04.png",
    "/bottom/color/5.png": "/bottom/color/bottom_05.png",
    "/bottom/color/6.png": "/bottom/color/bottom_06.png",
    "/bottom/color/7.png": "/bottom/color/bottom_07.png",
    "/bottom/color/8.png": "/bottom/color/bottom_08.png",
    "/dress/1.png": "/dress/dress_01.png",
    "/dress/2.png": "/dress/dress_02.png",
    "/dress/3.png": "/dress/dress_03.png",
    "/dress/4.png": "/dress/dress_04.png",
    "/dress/5.png": "/dress/dress_05.png",
    "/dress/6.png": "/dress/dress_06.png",
    "/dress/7.png": "/dress/dress_07.png",
    "/dress/COLORS/1.png": "/dress/COLORS/dress_01.png",
    "/dress/COLORS/2.png": "/dress/COLORS/dress_02.png",
    "/dress/COLORS/3.png": "/dress/COLORS/dress_03.png",
    "/dress/COLORS/4.png": "/dress/COLORS/dress_04.png",
    "/dress/COLORS/5.png": "/dress/COLORS/dress_05.png",
    "/dress/COLORS/6.png": "/dress/COLORS/dress_06.png",
    "/dress/COLORS/7.png": "/dress/COLORS/dress_07.png",
    "/EYEBROWS/1.png": "/EYEBROWS/eyebrows_01.png",
    "/EYEBROWS/2.png": "/EYEBROWS/eyebrows_02.png",
    "/EYEBROWS/3.png": "/EYEBROWS/eyebrows_03.png",
    "/EYEBROWS/4.png": "/EYEBROWS/eyebrows_04.png",
    "/EYEBROWS/5.png": "/EYEBROWS/eyebrows_05.png",
    "/EYELASHES/1.png": "/EYELASHES/eyelashes_01.png",
    "/EYELASHES/2.png": "/EYELASHES/eyelashes_02.png",
    "/EYELASHES/3.png": "/EYELASHES/eyelashes_03.png",
    "/EYELASHES/4.png": "/EYELASHES/eyelashes_04.png",
    "/EYELASHES/5.png": "/EYELASHES/eyelashes_05.png",
    "/gloves/1.png": "/gloves/gloves_01.png",
    "/gloves/2.png": "/gloves/gloves_02.png",
    "/gloves/3.png": "/gloves/gloves_03.png",
    "/gloves/4.png": "/gloves/gloves_04.png",
    "/gloves/5.png": "/gloves/gloves_05.png",
    "/gloves/6.png": "/gloves/gloves_06.png",
    "/gloves/COLOR/1.png": "/gloves/COLOR/gloves_01.png",
    "/gloves/COLOR/2.png": "/gloves/COLOR/gloves_02.png",
    "/gloves/COLOR/3.png": "/gloves/COLOR/gloves_03.png",
    "/gloves/COLOR/4.png": "/gloves/COLOR/gloves_04.png",
    "/gloves/COLOR/5.png": "/gloves/COLOR/gloves_05.png",
    "/gloves/COLOR/6.png": "/gloves/COLOR/gloves_06.png",
    "/hair/1.png": "/hair/hair_01.png",
    "/hair/10.png": "/hair/hair_10.png",
    "/hair/11.png": "/hair/hair_11.png",
    "/hair/12.png": "/hair/hair_12.png",
    "/hair/2.png": "/hair/hair_02.png",
    "/hair/3.png": "/hair/hair_03.png",
    "/hair/4.png": "/hair/hair_04.png",
    "/hair/5.png": "/hair/hair_05.png",
    "/hair/6.png": "/hair/hair_06.png",
    "/hair/7.png": "/hair/hair_07.png",
    "/hair/8.png": "/hair/hair_08.png",
    "/hair/9.png": "/hair/hair_09.png",
    "/hair/COLOR/1.png": "/hair/COLOR/hair_01.png",
    "/hair/COLOR/10.png": "/hair/COLOR/hair_10.png",
    "/hair/COLOR/10b.png": "/hair/COLOR/hair_10b.png",
    "/hair/COLOR/10c.png": "/hair/COLOR/hair_10c.png",
    "/hair/COLOR/10d.png": "/hair/COLOR/hair_10d.png",
    "/hair/COLOR/10e.png": "/hair/COLOR/hair_10e.png",
    "/hair/COLOR/10f.png": "/hair/COLOR/hair_10f.png",
    "/hair/COLOR/10g.png": "/hair/COLOR/hair_10g.png",
    "/hair/COLOR/10h.png": "/hair/COLOR/hair_10h.png",
    "/hair/COLOR/11.png": "/hair/COLOR/hair_11.png",
    "/hair/COLOR/11b.png": "/hair/COLOR/hair_11b.png",
    "/hair/COLOR/11c.png": "/hair/COLOR/hair_11c.png",
    "/hair/COLOR/11d.png": "/hair/COLOR/hair_11d.png",
    "/hair/COLOR/11e.png": "/hair/COLOR/hair_11e.png",
    "/hair/COLOR/11f.png": "/hair/COLOR/hair_11f.png",
    "/hair/COLOR/11g.png": "/hair/COLOR/hair_11g.png",
    "/hair/COLOR/11h.png": "/hair/COLOR/hair_11h.png",
    "/hair/COLOR/12.png": "/hair/COLOR/hair_12.png",
    "/hair/COLOR/12b.png": "/hair/COLOR/hair_12b.png",
    "/hair/COLOR/12c.png": "/hair/COLOR/hair_12c.png",
    "/hair/COLOR/12d.png": "/hair/COLOR/hair_12d.png",
    "/hair/COLOR/12e.png": "/hair/COLOR/hair_12e.png",
    "/hair/COLOR/12f.png": "/hair/COLOR/hair_12f.png",
    "/hair/COLOR/12g.png": "/hair/COLOR/hair_12g.png",
    "/hair/COLOR/12h.png": "/hair/COLOR/hair_12h.png",
    "/hair/COLOR/1b.png": "/hair/COLOR/hair_01b.png",
    "/hair/COLOR/1c.png": "/hair/COLOR/hair_01c.png",
    "/hair/COLOR/1d.png": "/hair/COLOR/hair_01d.png",
    "/hair/COLOR/1e.png": "/hair/COLOR/hair_01e.png",
    "/hair/COLOR/1f.png": "/hair/COLOR/hair_01f.png",
    "/hair/COLOR/1g.png": "/hair/COLOR/hair_01g.png",
    "/hair/COLOR/1h.png": "/hair/COLOR/hair_01h.png",
    "/hair/COLOR/2.png": "/hair/COLOR/hair_02.png",
    "/hair/COLOR/2b.png": "/hair/COLOR/hair_02b.png",
    "/hair/COLOR/2c.png": "/hair/COLOR/hair_02c.png",
    "/hair/COLOR/2d.png": "/hair/COLOR/hair_02d.png",
    "/hair/COLOR/2e.png": "/hair/COLOR/hair_02e.png",
    "/hair/COLOR/2f.png": "/hair/COLOR/hair_02f.png",
    "/hair/COLOR/2g.png": "/hair/COLOR/hair_02g.png",
    "/hair/COLOR/2h.png": "/hair/COLOR/hair_02h.png",
    "/hair/COLOR/3.png": "/hair/COLOR/hair_03.png",
    "/hair/COLOR/3b.png": "/hair/COLOR/hair_03b.png",
    "/hair/COLOR/3c.png": "/hair/COLOR/hair_03c.png",
    "/hair/COLOR/3d.png": "/hair/COLOR/hair_03d.png",
    "/hair/COLOR/3e.png": "/hair/COLOR/hair_03e.png",
    "/hair/COLOR/3f.png": "/hair/COLOR/hair_03f.png",
    "/hair/COLOR/3g.png": "/hair/COLOR/hair_03g.png",
    "/hair/COLOR/3h.png": "/hair/COLOR/hair_03h.png",
    "/hair/COLOR/4.png": "/hair/COLOR/hair_04.png",
    "/hair/COLOR/4b.png": "/hair/COLOR/hair_04b.png",
    "/hair/COLOR/4c.png": "/hair/COLOR/hair_04c.png",
    "/hair/COLOR/4d.png": "/hair/COLOR/hair_04d.png",
    "/hair/COLOR/4e.png": "/hair/COLOR/hair_04e.png",
    "/hair/COLOR/4f.png": "/hair/COLOR/hair_04f.png",
    "/hair/COLOR/4g.png": "/hair/COLOR/hair_04g.png",
    "/hair/COLOR/4h.png": "/hair/COLOR/hair_04h.png",
    "/hair/COLOR/5.png": "/hair/COLOR/hair_05.png",
    "/hair/COLOR/5b.png": "/hair/COLOR/hair_05b.png",
    "/hair/COLOR/5c.png": "/hair/COLOR/hair_05c.png",
    "/hair/COLOR/5d.png": "/hair/COLOR/hair_05d.png",
    "/hair/COLOR/5e.png": "/hair/COLOR/hair_05e.png",
    "/hair/COLOR/5f.png": "/hair/COLOR/hair_05f.png",
    "/hair/COLOR/5g.png": "/hair/COLOR/hair_05g.png",
    "/hair/COLOR/5h.png": "/hair/COLOR/hair_05h.png",
    "/hair/COLOR/6.png": "/hair/COLOR/hair_06.png",
    "/hair/COLOR/6b.png": "/hair/COLOR/hair_06b.png",
    "/hair/COLOR/6c.png": "/hair/COLOR/hair_06c.png",
    "/hair/COLOR/6d.png": "/hair/COLOR/hair_06d.png",
    "/hair/COLOR/6e.png": "/hair/COLOR/hair_06e.png",
    "/hair/COLOR/6f.png": "/hair/COLOR/hair_06f.png",
    "/hair/COLOR/6g.png": "/hair/COLOR/hair_06g.png",
    "/hair/COLOR/6h.png": "/hair/COLOR/hair_06h.png",
    "/hair/COLOR/7.png": "/hair/COLOR/hair_07.png",
    "/hair/COLOR/7b.png": "/hair/COLOR/hair_07b.png",
    "/hair/COLOR/7c.png": "/hair/COLOR/hair_07c.png",
    "/hair/COLOR/7d.png": "/hair/COLOR/hair_07d.png",
    "/hair/COLOR/7e.png": "/hair/COLOR/hair_07e.png",
    "/hair/COLOR/7f.png": "/hair/COLOR/hair_07f.png",
    "/hair/COLOR/7g.png": "/hair/COLOR/hair_07g.png",
    "/hair/COLOR/7h.png": "/hair/COLOR/hair_07h.png",
    "/hair/COLOR/8.png": "/hair/COLOR/hair_08.png",
    "/hair/COLOR/8b.png": "/hair/COLOR/hair_08b.png",
    "/hair/COLOR/8c.png": "/hair/COLOR/hair_08c.png",
    "/hair/COLOR/8d.png": "/hair/COLOR/hair_08d.png",
    "/hair/COLOR/8e.png": "/hair/COLOR/hair_08e.png",
    "/hair/COLOR/8f.png": "/hair/COLOR/hair_08f.png",
    "/hair/COLOR/8g.png": "/hair/COLOR/hair_08g.png",
    "/hair/COLOR/8h.png": "/hair/COLOR/hair_08h.png",
    "/hair/COLOR/9.png": "/hair/COLOR/hair_09.png",
    "/hair/COLOR/9b.png": "/hair/COLOR/hair_09b.png",
    "/hair/COLOR/9c.png": "/hair/COLOR/hair_09c.png",
    "/hair/COLOR/9d.png": "/hair/COLOR/hair_09d.png",
    "/hair/COLOR/9e.png": "/hair/COLOR/hair_09e.png",
    "/hair/COLOR/9f.png": "/hair/COLOR/hair_09f.png",
    "/hair/COLOR/9g.png": "/hair/COLOR/hair_09g.png",
    "/hair/COLOR/9h.png": "/hair/COLOR/hair_09h.png",
    "/hair_back/1.png": "/hair_back/hair_back_01.png",
    "/hair_back/10.png": "/hair_back/hair_back_10.png",
    "/hair_back/11.png": "/hair_back/hair_back_11.png",
    "/hair_back/12.png": "/hair_back/hair_back_12.png",
    "/hair_back/2.png": "/hair_back/hair_back_02.png",
    "/hair_back/3.png": "/hair_back/hair_back_03.png",
    "/hair_back/4.png": "/hair_back/hair_back_04.png",
    "/hair_back/5.png": "/hair_back/hair_back_05.png",
    "/hair_back/6.png": "/hair_back/hair_back_06.png",
    "/hair_back/7.png": "/hair_back/hair_back_07.png",
    "/hair_back/8.png": "/hair_back/hair_back_08.png",
    "/hair_back/9.png": "/hair_back/hair_back_09.png",
    "/hair_back/COLOR/1.png": "/hair_back/COLOR/hair_back_01.png",
    "/hair_back/COLOR/10.png": "/hair_back/COLOR/hair_back_10.png",
    "/hair_back/COLOR/10b.png": "/hair_back/COLOR/hair_back_10b.png",
    "/hair_back/COLOR/10c.png": "/hair_back/COLOR/hair_back_10c.png",
    "/hair_back/COLOR/10d.png": "/hair_back/COLOR/hair_back_10d.png",
    "/hair_back/COLOR/10e.png": "/hair_back/COLOR/hair_back_10e.png",
    "/hair_back/COLOR/10f.png": "/hair_back/COLOR/hair_back_10f.png",
    "/hair_back/COLOR/10g.png": "/hair_back/COLOR/hair_back_10g.png",
    "/hair_back/COLOR/10h.png": "/hair_back/COLOR/hair_back_10h.png",
    "/hair_back/COLOR/11.png": "/hair_back/COLOR/hair_back_11.png",
    "/hair_back/COLOR/11b.png": "/hair_back/COLOR/hair_back_11b.png",
    "/hair_back/COLOR/11c.png": "/hair_back/COLOR/hair_back_11c.png",
    "/hair_back/COLOR/11d.png": "/hair_back/COLOR/hair_back_11d.png",
    "/hair_back/COLOR/11e.png": "/hair_back/COLOR/hair_back_11e.png",
    "/hair_back/COLOR/11f.png": "/hair_back/COLOR/hair_back_11f.png",
    "/hair_back/COLOR/11g.png": "/hair_back/COLOR/hair_back_11g.png",
    "/hair_back/COLOR/11h.png": "/hair_back/COLOR/hair_back_11h.png",
    "/hair_back/COLOR/12.png": "/hair_back/COLOR/hair_back_12.png",
    "/hair_back/COLOR/12b.png": "/hair_back/COLOR/hair_back_12b.png",
    "/hair_back/COLOR/12c.png": "/hair_back/COLOR/hair_back_12c.png",
    "/hair_back/COLOR/12d.png": "/hair_back/COLOR/hair_back_12d.png",
    "/hair_back/COLOR/12e.png": "/hair_back/COLOR/hair_back_12e.png",
    "/hair_back/COLOR/12f.png": "/hair_back/COLOR/hair_back_12f.png",
    "/hair_back/COLOR/12g.png": "/hair_back/COLOR/hair_back_12g.png",
    "/hair_back/COLOR/12h.png": "/hair_back/COLOR/hair_back_12h.png",
    "/hair_back/COLOR/1b.png": "/hair_back/COLOR/hair_back_01b.png",
    "/hair_back/COLOR/1c.png": "/hair_back/COLOR/hair_back_01c.png",
    "/hair_back/COLOR/1d.png": "/hair_back/COLOR/hair_back_01d.png",
    "/hair_back/COLOR/1e.png": "/hair_back/COLOR/hair_back_01e.png",
    "/hair_back/COLOR/1f.png": "/hair_back/COLOR/hair_back_01f.png",
    "/hair_back/COLOR/1g.png": "/hair_back/COLOR/hair_back_01g.png",
    "/hair_back/COLOR/1h.png": "/hair_back/COLOR/hair_back_01h.png",
    "/hair_back/COLOR/2.png": "/hair_back/COLOR/hair_back_02.png",
    "/hair_back/COLOR/2b.png": "/hair_back/COLOR/hair_back_02b.png",
    "/hair_back/COLOR/2c.png": "/hair_back/COLOR/hair_back_02c.png",
    "/hair_back/COLOR/2d.png": "/hair_back/COLOR/hair_back_02d.png",
    "/hair_back/COLOR/2e.png": "/hair_back/COLOR/hair_back_02e.png",
    "/hair_back/COLOR/2f.png": "/hair_back/COLOR/hair_back_02f.png",
    "/hair_back/COLOR/2g.png": "/hair_back/COLOR/hair_back_02g.png",
    "/hair_back/COLOR/2h.png": "/hair_back/COLOR/hair_back_02h.png",
    "/hair_back/COLOR/3.png": "/hair_back/COLOR/hair_back_03.png",
    "/hair_back/COLOR/3b.png": "/hair_back/COLOR/hair_back_03b.png",
    "/hair_back/COLOR/3c.png": "/hair_back/COLOR/hair_back_03c.png",
    "/hair_back/COLOR/3d.png": "/hair_back/COLOR/hair_back_03d.png",
    "/hair_back/COLOR/3e.png": "/hair_back/COLOR/hair_back_03e.png",
    "/hair_back/COLOR/3f.png": "/hair_back/COLOR/hair_back_03f.png",
    "/hair_back/COLOR/3g.png": "/hair_back/COLOR/hair_back_03g.png",
    "/hair_back/COLOR/3h.png": "/hair_back/COLOR/hair_back_03h.png",
    "/hair_back/COLOR/4.png": "/hair_back/COLOR/hair_back_04.png",
    "/hair_back/COLOR/4b.png": "/hair_back/COLOR/hair_back_04b.png",
    "/hair_back/COLOR/4c.png": "/hair_back/COLOR/hair_back_04c.png",
    "/hair_back/COLOR/4d.png": "/hair_back/COLOR/hair_back_04d.png",
    "/hair_back/COLOR/4e.png": "/hair_back/COLOR/hair_back_04e.png",
    "/hair_back/COLOR/4f.png": "/hair_back/COLOR/hair_back_04f.png",
    "/hair_back/COLOR/4g.png": "/hair_back/COLOR/hair_back_04g.png",
    "/hair_back/COLOR/4h.png": "/hair_back/COLOR/hair_back_04h.png",
    "/hair_back/COLOR/5.png": "/hair_back/COLOR/hair_back_05.png",
    "/hair_back/COLOR/5b.png": "/hair_back/COLOR/hair_back_05b.png",
    "/hair_back/COLOR/5c.png": "/hair_back/COLOR/hair_back_05c.png",
    "/hair_back/COLOR/5d.png": "/hair_back/COLOR/hair_back_05d.png",
    "/hair_back/COLOR/5e.png": "/hair_back/COLOR/hair_back_05e.png",
    "/hair_back/COLOR/5f.png": "/hair_back/COLOR/hair_back_05f.png",
    "/hair_back/COLOR/5g.png": "/hair_back/COLOR/hair_back_05g.png",
    "/hair_back/COLOR/5h.png": "/hair_back/COLOR/hair_back_05h.png",
    "/hair_back/COLOR/6.png": "/hair_back/COLOR/hair_back_06.png",
    "/hair_back/COLOR/6b.png": "/hair_back/COLOR/hair_back_06b.png",
    "/hair_back/COLOR/6c.png": "/hair_back/COLOR/hair_back_06c.png",
    "/hair_back/COLOR/6d.png": "/hair_back/COLOR/hair_back_06d.png",
    "/hair_back/COLOR/6e.png": "/hair_back/COLOR/hair_back_06e.png",
    "/hair_back/COLOR/6f.png": "/hair_back/COLOR/hair_back_06f.png",
    "/hair_back/COLOR/6g.png": "/hair_back/COLOR/hair_back_06g.png",
    "/hair_back/COLOR/6h.png": "/hair_back/COLOR/hair_back_06h.png",
    "/hair_back/COLOR/7.png": "/hair_back/COLOR/hair_back_07.png",
    "/hair_back/COLOR/7b.png": "/hair_back/COLOR/hair_back_07b.png",
    "/hair_back/COLOR/7c.png": "/hair_back/COLOR/hair_back_07c.png",
    "/hair_back/COLOR/7d.png": "/hair_back/COLOR/hair_back_07d.png",
    "/hair_back/COLOR/7e.png": "/hair_back/COLOR/hair_back_07e.png",
    "/hair_back/COLOR/7f.png": "/hair_back/COLOR/hair_back_07f.png",
    "/hair_back/COLOR/7g.png": "/hair_back/COLOR/hair_back_07g.png",
    "/hair_back/COLOR/7h.png": "/hair_back/COLOR/hair_back_07h.png",
    "/hair_back/COLOR/8.png": "/hair_back/COLOR/hair_back_08.png",
    "/hair_back/COLOR/8b.png": "/hair_back/COLOR/hair_back_08b.png",
    "/hair_back/COLOR/8c.png": "/hair_back/COLOR/hair_back_08c.png",
    "/hair_back/COLOR/8d.png": "/hair_back/COLOR/hair_back_08d.png",
    "/hair_back/COLOR/8e.png": "/hair_back/COLOR/hair_back_08e.png",
    "/hair_back/COLOR/8f.png": "/hair_back/COLOR/hair_back_08f.png",
    "/hair_back/COLOR/8g.png": "/hair_back/COLOR/hair_back_08g.png",
    "/hair_back/COLOR/8h.png": "/hair_back/COLOR/hair_back_08h.png",
    "/hair_back/COLOR/9.png": "/hair_back/COLOR/hair_back_09.png",
    "/hair_back/COLOR/9b.png": "/hair_back/COLOR/hair_back_09b.png",
    "/hair_back/COLOR/9c.png": "/hair_back/COLOR/hair_back_09c.png",
    "/hair_back/COLOR/9d.png": "/hair_back/COLOR/hair_back_09d.png",
    "/hair_back/COLOR/9e.png": "/hair_back/COLOR/hair_back_09e.png",
    "/hair_back/COLOR/9f.png": "/hair_back/COLOR/hair_back_09f.png",
    "/hair_back/COLOR/9g.png": "/hair_back/COLOR/hair_back_09g.png",
    "/hair_back/COLOR/9h.png": "/hair_back/COLOR/hair_back_09h.png",
    "/hair_bonus/1.png": "/hair_bonus/hair_bonus_01.png",
    "/hair_bonus/2.png": "/hair_bonus/hair_bonus_02.png",
    "/hair_bonus/3.png": "/hair_bonus/hair_bonus_03.png",
    "/hair_bonus/4.png": "/hair_bonus/hair_bonus_04.png",
    "/hair_bonus/5.png": "/hair_bonus/hair_bonus_05.png",
    "/hair_bonus/COLOR/1.png": "/hair_bonus/COLOR/hair_bonus_01.png",
    "/hair_bonus/COLOR/1b.png": "/hair_bonus/COLOR/hair_bonus_01b.png",
    "/hair_bonus/COLOR/1c.png": "/hair_bonus/COLOR/hair_bonus_01c.png",
    "/hair_bonus/COLOR/1d.png": "/hair_bonus/COLOR/hair_bonus_01d.png",
    "/hair_bonus/COLOR/1e.png": "/hair_bonus/COLOR/hair_bonus_01e.png",
    "/hair_bonus/COLOR/1f.png": "/hair_bonus/COLOR/hair_bonus_01f.png",
    "/hair_bonus/COLOR/1g.png": "/hair_bonus/COLOR/hair_bonus_01g.png",
    "/hair_bonus/COLOR/1h.png": "/hair_bonus/COLOR/hair_bonus_01h.png",
    "/hair_bonus/COLOR/2.png": "/hair_bonus/COLOR/hair_bonus_02.png",
    "/hair_bonus/COLOR/2b.png": "/hair_bonus/COLOR/hair_bonus_02b.png",
    "/hair_bonus/COLOR/2c.png": "/hair_bonus/COLOR/hair_bonus_02c.png",
    "/hair_bonus/COLOR/2d.png": "/hair_bonus/COLOR/hair_bonus_02d.png",
    "/hair_bonus/COLOR/2e.png": "/hair_bonus/COLOR/hair_bonus_02e.png",
    "/hair_bonus/COLOR/2f.png": "/hair_bonus/COLOR/hair_bonus_02f.png",
    "/hair_bonus/COLOR/2g.png": "/hair_bonus/COLOR/hair_bonus_02g.png",
    "/hair_bonus/COLOR/2h.png": "/hair_bonus/COLOR/hair_bonus_02h.png",
    "/hair_bonus/COLOR/3.png": "/hair_bonus/COLOR/hair_bonus_03.png",
    "/hair_bonus/COLOR/3b.png": "/hair_bonus/COLOR/hair_bonus_03b.png",
    "/hair_bonus/COLOR/3c.png": "/hair_bonus/COLOR/hair_bonus_03c.png",
    "/hair_bonus/COLOR/3d.png": "/hair_bonus/COLOR/hair_bonus_03d.png",
    "/hair_bonus/COLOR/3e.png": "/hair_bonus/COLOR/hair_bonus_03e.png",
    "/hair_bonus/COLOR/3f.png": "/hair_bonus/COLOR/hair_bonus_03f.png",
    "/hair_bonus/COLOR/3g.png": "/hair_bonus/COLOR/hair_bonus_03g.png",
    "/hair_bonus/COLOR/3h.png": "/hair_bonus/COLOR/hair_bonus_03h.png",
    "/hair_bonus/COLOR/4.png": "/hair_bonus/COLOR/hair_bonus_04.png",
    "/hair_bonus/COLOR/4b.png": "/hair_bonus/COLOR/hair_bonus_04b.png",
    "/hair_bonus/COLOR/4c.png": "/hair_bonus/COLOR/hair_bonus_04c.png",
    "/hair_bonus/COLOR/4d.png": "/hair_bonus/COLOR/hair_bonus_04d.png",
    "/hair_bonus/COLOR/4e.png": "/hair_bonus/COLOR/hair_bonus_04e.png",
    "/hair_bonus/COLOR/4f.png": "/hair_bonus/COLOR/hair_bonus_04f.png",
    "/hair_bonus/COLOR/4g.png": "/hair_bonus/COLOR/hair_bonus_04g.png",
    "/hair_bonus/COLOR/4h.png": "/hair_bonus/COLOR/hair_bonus_04h.png",
    "/hair_bonus/COLOR/5.png": "/hair_bonus/COLOR/hair_bonus_05.png",
    "/hair_bonus/COLOR/5b.png": "/hair_bonus/COLOR/hair_bonus_05b.png",
    "/hair_bonus/COLOR/5c.png": "/hair_bonus/COLOR/hair_bonus_05c.png",
    "/hair_bonus/COLOR/5d.png": "/hair_bonus/COLOR/hair_bonus_05d.png",
    "/hair_bonus/COLOR/5e.png": "/hair_bonus/COLOR/hair_bonus_05e.png",
    "/hair_bonus/COLOR/5f.png": "/hair_bonus/COLOR/hair_bonus_05f.png",
    "/hair_bonus/COLOR/5g.png": "/hair_bonus/COLOR/hair_bonus_05g.png",
    "/hair_bonus/COLOR/5h.png": "/hair_bonus/COLOR/hair_bonus_05h.png",
    "/MOUTH/1.png": "/MOUTH/mouth_01.png",
    "/MOUTH/10.png": "/MOUTH/mouth_10.png",
    "/MOUTH/11.png": "/MOUTH/mouth_11.png",
    "/MOUTH/12.png": "/MOUTH/mouth_12.png",
    "/MOUTH/13.png": "/MOUTH/mouth_13.png",
    "/MOUTH/14.png": "/MOUTH/mouth_14.png",
    "/MOUTH/15.png": "/MOUTH/mouth_15.png",
    "/MOUTH/16.png": "/MOUTH/mouth_16.png",
    "/MOUTH/17.png": "/MOUTH/mouth_17.png",
    "/MOUTH/18.png": "/MOUTH/mouth_18.png",
    "/MOUTH/19.png": "/MOUTH/mouth_19.png",
    "/MOUTH/2.png": "/MOUTH/mouth_02.png",
    "/MOUTH/20.png": "/MOUTH/mouth_20.png",
    "/MOUTH/3.png": "/MOUTH/mouth_03.png",
    "/MOUTH/4.png": "/MOUTH/mouth_04.png",
    "/MOUTH/5.png": "/MOUTH/mouth_05.png",
    "/MOUTH/6.png": "/MOUTH/mouth_06.png",
    "/MOUTH/7.png": "/MOUTH/mouth_07.png",
    "/MOUTH/8.png": "/MOUTH/mouth_08.png",
    "/MOUTH/9.png": "/MOUTH/mouth_09.png",
    "/PUPILS/1.png": "/PUPILS/pupils_01.png",
    "/PUPILS/10.png": "/PUPILS/pupils_10.png",
    "/PUPILS/11.png": "/PUPILS/pupils_11.png",
    "/PUPILS/12.png": "/PUPILS/pupils_12.png",
    "/PUPILS/13.png": "/PUPILS/pupils_13.png",
    "/PUPILS/14.png": "/PUPILS/pupils_14.png",
    "/PUPILS/15.png": "/PUPILS/pupils_15.png",
    "/PUPILS/16.png": "/PUPILS/pupils_16.png",
    "/PUPILS/2.png": "/PUPILS/pupils_02.png",
    "/PUPILS/3.png": "/PUPILS/pupils_03.png",
    "/PUPILS/4.png": "/PUPILS/pupils_04.png",
    "/PUPILS/5.png": "/PUPILS/pupils_05.png",
    "/PUPILS/6.png": "/PUPILS/pupils_06.png",
    "/PUPILS/7.png": "/PUPILS/pupils_07.png",
    "/PUPILS/8.png": "/PUPILS/pupils_08.png",
    "/PUPILS/9.png": "/PUPILS/pupils_09.png",
    "/shoes/1.png": "/shoes/shoes_01.png",
    "/shoes/2.png": "/shoes/shoes_02.png",
    "/shoes/3.png": "/shoes/shoes_03.png",
    "/shoes/4.png": "/shoes/shoes_04.png",
    "/shoes/COLOR/1.png": "/shoes/COLOR/shoes_01.png",
    "/shoes/COLOR/2.png": "/shoes/COLOR/shoes_02.png",
    "/shoes/COLOR/3.png": "/shoes/COLOR/shoes_03.png",
    "/shoes/COLOR/4.png": "/shoes/COLOR/shoes_04.png",
    "/top/1.png": "/top/top_01.png",
    "/top/10.png": "/top/top_10.png",
    "/top/11.png": "/top/top_11.png",
    "/top/12.png": "/top/top_12.png",
    "/top/2.png": "/top/top_02.png",
    "/top/3.png": "/top/top_03.png",
    "/top/4.png": "/top/top_04.png",
    "/top/5.png": "/top/top_05.png",
    "/top/6.png": "/top/top_06.png",
    "/top/7.png": "/top/top_07.png",
    "/top/8.png": "/top/top_08.png",
    "/top/9.png": "/top/top_09.png",
    "/top/colors/1.png": "/top/colors/top_01.png",
    "/top/colors/10.png": "/top/colors/top_10.png",
    "/top/colors/11.png": "/top/colors/top_11.png",
    "/top/colors/12.png": "/top/colors/top_12.png",
    "/top/colors/2.png": "/top/colors/top_02.png",
    "/top/colors/3.png": "/top/colors/top_03.png",
    "/top/colors/4.png": "/top/colors/top_04.png",
    "/top/colors/5.png": "/top/colors/top_05.png",
    "/top/colors/6.png": "/top/colors/top_06.png",
    "/top/colors/7.png": "/top/colors/top_07.png",
    "/top/colors/8.png": "/top/colors/top_08.png",
    "/top/colors/9.png": "/top/colors/top_09.png"
  },
  "defaults": {
    "body": "body_01.png",
    "pupils": "pupils_01.png",
    "eyebrows": "eyebrows_01.png",
    "eyelashes": "eyelashes_01.png"
  }
}